surface_roughness-0.0.3.dist-info/RECORD
surface_roughness-0.0.3.dist-info/LICENSE
surface_roughness-0.0.3.dist-info/WHEEL
surface_roughness-0.0.3.dist-info/top_level.txt
surface_roughness-0.0.3.dist-info/METADATA
surface_roughness/_sampling_utils.py
surface_roughness/_profile.py
surface_roughness/roughness.py
surface_roughness/__init__.py
surface_roughness/_geometry_utils.py
surface_roughness/_roughness_cppimpl.cpython-310-darwin.so
surface_roughness/sampling.py
surface_roughness/roughness_impl.py
surface_roughness/_roughness_pyimpl/_DirectionalRoughness.py
surface_roughness/_roughness_pyimpl/__init__.py
surface_roughness/_roughness_pyimpl/_TINBasedRoughness.py
