Metadata-Version: 2.1
Name: surface-roughness
Version: 0.0.3
Summary: Surface roughness calculation with Python
Home-page: https://github.com/e-mags/pysurfaceroughness
Author: Earl Magsipoc
Author-email: e.magsipoc@mail.utoronto.ca
License: MIT
Requires-Python: >=3.9
License-File: LICENSE
Requires-Dist: scipy
Requires-Dist: meshio
Requires-Dist: tqdm
Requires-Dist: numpy
Requires-Dist: numexpr
Requires-Dist: pandas
Requires-Dist: matplotlib
Requires-Dist: mplstereonet
Requires-Dist: shapely
